async_backlog_limiter/__init__.py
async_backlog_limiter-0.1.3.dist-info/LICENSE
async_backlog_limiter-0.1.3.dist-info/METADATA
async_backlog_limiter-0.1.3.dist-info/WHEEL
async_backlog_limiter-0.1.3.dist-info/RECORD
