Metadata-Version: 2.3
Name: async-backlog-limiter
Version: 0.1.3
Summary: Async concurrency and queue limiter with server-style backlog control.
License: MIT
Keywords: asyncio,rate limiter,concurrency,backlog,throttling,limiter
Requires-Python: >=3.12
Classifier: Development Status :: 5 - Production/Stable
Classifier: Framework :: AsyncIO
Classifier: Intended Audience :: Developers
Classifier: License :: OSI Approved :: MIT License
Classifier: Operating System :: OS Independent
Classifier: Programming Language :: Python :: 3
Classifier: Programming Language :: Python :: 3.12
Classifier: Programming Language :: Python :: 3.13
Classifier: Programming Language :: Python :: 3.14
Classifier: Topic :: Internet
Classifier: Topic :: Software Development :: Libraries
Classifier: Topic :: Utilities
Classifier: Typing :: Typed
Project-URL: Documentation, https://github.com/shafa-dev/async_backlog_limiter/blob/main/README.md
Project-URL: Homepage, https://github.com/shafa-dev/async_backlog_limiter
Project-URL: Repository, https://github.com/shafa-dev/async_backlog_limiter
